{"title":"IKnowThatGirl - Spinner's First Sex Tape - Kylie Nicole [720p].m","uid":12050361,"size":688860153,"categoryP":"porn","categoryS":"hd___movies","magnet":"?xt=urn:btih:040d6987007c4092ed514035e8f8f2e99ca6944f&amp;dn=IKnowThatGirl+-+Spinner%27s+First+Sex+Tape+-+Kylie+Nicole+%5B720p%5D.m&amp;tr=udp%3A%2F%2Ftracker.openbittorrent.com%3A80&amp;tr=udp%3A%2F%2Fopen.demonii.com%3A1337&amp;tr=udp%3A%2F%2Ftracker.coppersurfer.tk%3A6969&amp;tr=udp%3A%2F%2Fexodus.desync.com%3A6969","seeders":1,"leechers":0,"uploader":"1.No.1","files":1,"time":1434984685,"description":"IKnowThatGirl - Spinner's First Sex Tape - Kylie Nicole [720p].mp4\n\n2015, Couples Fantasies, All Sex, Deepthroat, Doggystyle, Oral, Hardcore, HD, XXX, Adult\n\n656.95 MB\n\nScreens\n &lt;a href=&quot;\nhttp://imgcentral.com/viewer.php?file=09204712908521885048.jpg&quot; rel=&quot;nofollow&quot; target=&quot;_NEW&quot;&gt;\nhttp://imgcentral.com/viewer.php?file=09204712908521885048.jpg&lt;/a&gt;\n &lt;a href=&quot;\nhttp://imgcentral.com/viewer.php?file=55736707188710668759.jpg&quot; rel=&quot;nofollow&quot; target=&quot;_NEW&quot;&gt;\nhttp://imgcentral.com/viewer.php?file=55736707188710668759.jpg&lt;/a&gt;\n &lt;a href=&quot;\nhttp://imgcentral.com/viewer.php?file=34081248422981888226.jpg&quot; rel=&quot;nofollow&quot; target=&quot;_NEW&quot;&gt;\nhttp://imgcentral.com/viewer.php?file=34081248422981888226.jpg&lt;/a&gt;\n &lt;a href=&quot;\nhttp://imgcentral.com/viewer.php?file=92435904908647651181.jpg&quot; rel=&quot;nofollow&quot; target=&quot;_NEW&quot;&gt;\nhttp://imgcentral.com/viewer.php?file=92435904908647651181.jpg&lt;/a&gt;","torrent":{"xt":"urn:btih:040d6987007c4092ed514035e8f8f2e99ca6944f","amp;dn":"IKnowThatGirl+-+Spinner%27s+First+Sex+Tape+-+Kylie+Nicole+%5B720p%5D.m","amp;tr":["udp%3A%2F%2Ftracker.openbittorrent.com%3A80","udp%3A%2F%2Fopen.demonii.com%3A1337","udp%3A%2F%2Ftracker.coppersurfer.tk%3A6969","udp%3A%2F%2Fexodus.desync.com%3A6969"],"infoHash":"040d6987007c4092ed514035e8f8f2e99ca6944f","infoHashBuffer":{"type":"Buffer","data":[4,13,105,135,0,124,64,146,237,81,64,53,232,248,242,233,156,166,148,79]},"announce":[],"urlList":[]}}