{"title":"Nebenan#17","uid":7955133,"size":732432679,"categoryP":"porn","categoryS":"movies","magnet":"?xt=urn:btih:04f6a5d42bcd82514f60c3bc4cb9c8b5cb0490ae&amp;dn=Nebenan%2317&amp;tr=udp%3A%2F%2Ftracker.openbittorrent.com%3A80&amp;tr=udp%3A%2F%2Fopen.demonii.com%3A1337&amp;tr=udp%3A%2F%2Ftracker.coppersurfer.tk%3A6969&amp;tr=udp%3A%2F%2Fexodus.desync.com%3A6969","seeders":1,"leechers":0,"uploader":"Programsmith","files":-1,"time":1356397563,"description":"Year: 2009\nCountry: Germany\nGenre: Amateurs, All Sex, Anal, Legal Teen, Threesome\nDuration: 1:25:01\n\nDescription:\n \ntechnical characteristics\nVideo quality: DVDRip\nVideo format: AVI\nVideo codec: XviD\nAudio: MP3\nVideo: XviD 576 x 320 25.000fps 980Kbps\nAudio: MPEG (Audiolayer 3) 156Kbps 48.0KHz 2 channels 1 stream\n\n &lt;a href=&quot;\nhttp://imgload.me/img-50d8edaab73bb.html&quot; rel=&quot;nofollow&quot; target=&quot;_NEW&quot;&gt;\nhttp://imgload.me/img-50d8edaab73bb.html&lt;/a&gt; ","torrent":{"xt":"urn:btih:04f6a5d42bcd82514f60c3bc4cb9c8b5cb0490ae","amp;dn":"Nebenan%2317","amp;tr":["udp%3A%2F%2Ftracker.openbittorrent.com%3A80","udp%3A%2F%2Fopen.demonii.com%3A1337","udp%3A%2F%2Ftracker.coppersurfer.tk%3A6969","udp%3A%2F%2Fexodus.desync.com%3A6969"],"infoHash":"04f6a5d42bcd82514f60c3bc4cb9c8b5cb0490ae","infoHashBuffer":{"type":"Buffer","data":[4,246,165,212,43,205,130,81,79,96,195,188,76,185,200,181,203,4,144,174]},"announce":[],"urlList":[]}}