{"title":"Bella Le Garage (2013)","uid":8431541,"size":545557494,"categoryP":"porn","categoryS":"movies","magnet":"?xt=urn:btih:08d188c5bd553b439436cc13ef4392d4c72cba66&amp;dn=Bella+Le+Garage+%282013%29&amp;tr=udp%3A%2F%2Ftracker.openbittorrent.com%3A80&amp;tr=udp%3A%2F%2Fopen.demonii.com%3A1337&amp;tr=udp%3A%2F%2Ftracker.coppersurfer.tk%3A6969&amp;tr=udp%3A%2F%2Fexodus.desync.com%3A6969","seeders":1,"leechers":0,"uploader":"gatasalvaje","files":-1,"time":1367512968,"description":"Bella Le Garage (2013)\n &lt;a href=&quot;\nhttp://www.dorcelvision.com/studios/Marc_Dorcel/6522/Bella_Le_Garage&quot; rel=&quot;nofollow&quot; target=&quot;_NEW&quot;&gt;\nhttp://www.dorcelvision.com/studios/Marc_Dorcel/6522/Bella_Le_Garage&lt;/a&gt;\n\nName: Bella: Le Garage\nRelease date: 2013\nGenre: Amateur, Gang Bang, All sex, Facial\nDuration: 00:44:15\nCountry: France\nStudio: Marc Dorcel\nStarring: Bella\n\nDescription\nThe fantasy of young Bella, 20 years was to be taken quite intensely by several guys at once, and by guys a little seedy, a little punks, a little hard. For its sequence, Herve has taken to a garage, where she found herself surrounded by five guys who were waiting for a thing to fuck every hole. Despite her young age, she literally jumped on these cocks hired just for her. She sucked and was loaded into the furnace in her pussy, moved like a bitch in heat to enjoy like never before.\n\nQuality: DVDRip\nFormat: AVI\nVideo: Xvid 640x360 25.00fps 1499kbps\nSound: MPEG Audio Layer 3 44100Hz stereo 128kbps\nSize: 520 MB","torrent":{"xt":"urn:btih:08d188c5bd553b439436cc13ef4392d4c72cba66","amp;dn":"Bella+Le+Garage+%282013%29","amp;tr":["udp%3A%2F%2Ftracker.openbittorrent.com%3A80","udp%3A%2F%2Fopen.demonii.com%3A1337","udp%3A%2F%2Ftracker.coppersurfer.tk%3A6969","udp%3A%2F%2Fexodus.desync.com%3A6969"],"infoHash":"08d188c5bd553b439436cc13ef4392d4c72cba66","infoHashBuffer":{"type":"Buffer","data":[8,209,136,197,189,85,59,67,148,54,204,19,239,67,146,212,199,44,186,102]},"announce":[],"urlList":[]}}