{"title":"Royal Cousins At War S02E06 HDTV XviD-AFG [P2PDL]","uid":9581237,"size":520601030,"categoryP":"video","categoryS":"tv_shows","magnet":"?xt=urn:btih:12ba7658697b9661ea9e7c6f1cddccdbfe946fee&amp;dn=Royal+Cousins+At+War+S02E06+HDTV+XviD-AFG+%5BP2PDL%5D&amp;tr=udp%3A%2F%2Ftracker.openbittorrent.com%3A80&amp;tr=udp%3A%2F%2Fopen.demonii.com%3A1337&amp;tr=udp%3A%2F%2Ftracker.coppersurfer.tk%3A6969&amp;tr=udp%3A%2F%2Fexodus.desync.com%3A6969","seeders":1,"leechers":0,"uploader":"TeX","files":4,"time":1391771346,"description":"Royal.Cousins.At.War.S02E06.HDTV.XviD-AFG\n\nInfo:\nFile Name...........: Royal.Cousins.At.War.S02E06.HDTV.XviD-AFG\nRuntime.............: 58mn 58s\nFile Size...........: 496.5 MiB\nFormat..............: AVI\nVideo Bitrate.......: 1 177 Kbps\nVideo Codec.........: MPEG-4 Visual Advanced Simple@L5\nAspect Ratio........: 16:9\nResolution..........: 640x360 pixels\nFrame Rate..........: 25.000 fps\nAudio Codec.........: MPEG Audio Layer 3\nChannels............: 2 channels\nSampling Rate.......: 48.0 KHz\nBitrate.............: 128 Kbps\n\n\n\nScreenshots: &lt;a href=&quot;\nhttp://beeimg.com/view/q3492329216/&quot; rel=&quot;nofollow&quot; target=&quot;_NEW&quot;&gt;\nhttp://beeimg.com/view/q3492329216/&lt;/a&gt;  &lt;a href=&quot;\nhttp://beeimg.com/view/z2705412892/&quot; rel=&quot;nofollow&quot; target=&quot;_NEW&quot;&gt;\nhttp://beeimg.com/view/z2705412892/&lt;/a&gt;","torrent":{"xt":"urn:btih:12ba7658697b9661ea9e7c6f1cddccdbfe946fee","amp;dn":"Royal+Cousins+At+War+S02E06+HDTV+XviD-AFG+%5BP2PDL%5D","amp;tr":["udp%3A%2F%2Ftracker.openbittorrent.com%3A80","udp%3A%2F%2Fopen.demonii.com%3A1337","udp%3A%2F%2Ftracker.coppersurfer.tk%3A6969","udp%3A%2F%2Fexodus.desync.com%3A6969"],"infoHash":"12ba7658697b9661ea9e7c6f1cddccdbfe946fee","infoHashBuffer":{"type":"Buffer","data":[18,186,118,88,105,123,150,97,234,158,124,111,28,221,204,219,254,148,111,238]},"announce":[],"urlList":[]}}