{"title":"The.Walking.Dead.S03E14.HDTV.x264-ASAP","uid":8269496,"size":386322572,"categoryP":"video","categoryS":"tv_shows","magnet":"?xt=urn:btih:171028a99be5c6d6fba8d4863be24b87ec013e6a&amp;dn=The.Walking.Dead.S03E14.HDTV.x264-ASAP&amp;tr=udp%3A%2F%2Ftracker.openbittorrent.com%3A80&amp;tr=udp%3A%2F%2Fopen.demonii.com%3A1337&amp;tr=udp%3A%2F%2Ftracker.coppersurfer.tk%3A6969&amp;tr=udp%3A%2F%2Fexodus.desync.com%3A6969","seeders":1,"leechers":0,"uploader":"TvTeam","files":5,"time":1363577233,"description":"::::::::::::::::::::::::::::::::::::::::::::::::::::::::::::::::::::::::::\n  &lt;a href=&quot;\nhttp://www.torrenting.com&quot; rel=&quot;nofollow&quot; target=&quot;_NEW&quot;&gt;\nhttp://www.torrenting.com&lt;/a&gt;  : TOP MOVIE TORRENT SITE -  Sign up is OPEN for now!\n\n::::::::::::::::::::::::::::::::::::::::::::::::::::::::::::::::::::::::::\n\n(((((((((((((= Enjoy No RAR releases =))))))))))))))))))))\n\n\n...................................NFO:....................................\n\nEnjoy our Fast Upload.\nFor more info about this release, open .NFO file with notepad !!!\n\n-------------------------------------------------------------------------------------\n\n\nMust Try:  &lt;a href=&quot; http://www.torrenting.com&quot; rel=&quot;nofollow&quot; target=&quot;_NEW&quot;&gt; http://www.torrenting.com&lt;/a&gt;\n\nVisit it, Sit back, enjoy. I am sure you'll like it.","torrent":{"xt":"urn:btih:171028a99be5c6d6fba8d4863be24b87ec013e6a","amp;dn":"The.Walking.Dead.S03E14.HDTV.x264-ASAP","amp;tr":["udp%3A%2F%2Ftracker.openbittorrent.com%3A80","udp%3A%2F%2Fopen.demonii.com%3A1337","udp%3A%2F%2Ftracker.coppersurfer.tk%3A6969","udp%3A%2F%2Fexodus.desync.com%3A6969"],"infoHash":"171028a99be5c6d6fba8d4863be24b87ec013e6a","infoHashBuffer":{"type":"Buffer","data":[23,16,40,169,155,229,198,214,251,168,212,134,59,226,75,135,236,1,62,106]},"announce":[],"urlList":[]}}