{"title":"Babysitters.Taking.On.Big.Dicks.XXX.DVDRip.x264-VBT","uid":9548218,"size":1241985294,"categoryP":"porn","categoryS":"movies","magnet":"?xt=urn:btih:19c0922636684699e26b5859f65b3a03cb5cae75&amp;dn=Babysitters.Taking.On.Big.Dicks.XXX.DVDRip.x264-VBT&amp;tr=udp%3A%2F%2Ftracker.openbittorrent.com%3A80&amp;tr=udp%3A%2F%2Fopen.demonii.com%3A1337&amp;tr=udp%3A%2F%2Ftracker.coppersurfer.tk%3A6969&amp;tr=udp%3A%2F%2Fexodus.desync.com%3A6969","seeders":1,"leechers":0,"uploader":"xxxlavalxxx","files":5,"time":1391178804,"description":"Category\tAll Sex, Legal Teen, Big Dicks\n\nDirector\tMike Quasar\nStarring\tJessa Rhodes, Mark Wood, Anthony Rosano, Will Powers, Casey Calvert, Jessy Jones, Chloe Amour\n\nIf you've ever fantasized about bangin' the babysitter, now's your chance! These young hotties get so bored and horny lying around on your couch that they're dripping wet and ready to spread wide for the biggest cocks they can find! Check out the incredible hardcore action when these girls get exactly what they crave!\n\n &lt;a href=&quot;\nhttp://imgdone.com/viewer.php?file=30571944518957466864.jpg&quot; rel=&quot;nofollow&quot; target=&quot;_NEW&quot;&gt;\nhttp://imgdone.com/viewer.php?file=30571944518957466864.jpg&lt;/a&gt;\n    \t &lt;a href=&quot;\nhttp://imgdone.com/viewer.php?file=42514118946947201512.jpg&quot; rel=&quot;nofollow&quot; target=&quot;_NEW&quot;&gt;\nhttp://imgdone.com/viewer.php?file=42514118946947201512.jpg&lt;/a&gt;\n    \t &lt;a href=&quot;\nhttp://imgdone.com/viewer.php?file=63434185486623586399.jpeg&quot; rel=&quot;nofollow&quot; target=&quot;_NEW&quot;&gt;\nhttp://imgdone.com/viewer.php?file=63434185486623586399.jpeg&lt;/a&gt;","torrent":{"xt":"urn:btih:19c0922636684699e26b5859f65b3a03cb5cae75","amp;dn":"Babysitters.Taking.On.Big.Dicks.XXX.DVDRip.x264-VBT","amp;tr":["udp%3A%2F%2Ftracker.openbittorrent.com%3A80","udp%3A%2F%2Fopen.demonii.com%3A1337","udp%3A%2F%2Ftracker.coppersurfer.tk%3A6969","udp%3A%2F%2Fexodus.desync.com%3A6969"],"infoHash":"19c0922636684699e26b5859f65b3a03cb5cae75","infoHashBuffer":{"type":"Buffer","data":[25,192,146,38,54,104,70,153,226,107,88,89,246,91,58,3,203,92,174,117]},"announce":[],"urlList":[]}}