{"title":"LetsTryAnal - Kimberly Kendall (Busty Honey Stuffs her Asshole","uid":15206846,"size":447626330,"categoryP":"porn","categoryS":"movie_clips","magnet":"?xt=urn:btih:20f6fcc0d58abdd5085e898761fb2128c775888e&amp;dn=+LetsTryAnal+-+Kimberly+Kendall+%28Busty+Honey+Stuffs+her+Asshole+&amp;tr=udp%3A%2F%2Ftracker.leechers-paradise.org%3A6969&amp;tr=udp%3A%2F%2Fzer0day.ch%3A1337&amp;tr=udp%3A%2F%2Fopen.demonii.com%3A1337&amp;tr=udp%3A%2F%2Ftracker.coppersurfer.tk%3A6969&amp;tr=udp%3A%2F%2Fexodus.desync.com%3A6969","seeders":1,"leechers":0,"uploader":"codho","files":1,"time":1467633235,"description":"LetsTryAnal - Kimberly Kendall (Busty Honey Stuffs her Asshole / Mofos) sd Pre relrease NEW July 06, 2016 \r\n\r\n\r\n\r\nScreenshots :\r\n\r\n\r\n \nhttp://imgaah.com/viewer.php?file=35246993374794071803.jpg\r\n \nhttp://imgaah.com/viewer.php?file=56563722332491574911.jpeg\r\n\r\n \nhttp://imgaah.com/viewer.php?file=48787140727897687714.jpeg","torrent":{"xt":"urn:btih:20f6fcc0d58abdd5085e898761fb2128c775888e","amp;dn":"+LetsTryAnal+-+Kimberly+Kendall+%28Busty+Honey+Stuffs+her+Asshole+","amp;tr":["udp%3A%2F%2Ftracker.leechers-paradise.org%3A6969","udp%3A%2F%2Fzer0day.ch%3A1337","udp%3A%2F%2Fopen.demonii.com%3A1337","udp%3A%2F%2Ftracker.coppersurfer.tk%3A6969","udp%3A%2F%2Fexodus.desync.com%3A6969"],"infoHash":"20f6fcc0d58abdd5085e898761fb2128c775888e","infoHashBuffer":{"type":"Buffer","data":[32,246,252,192,213,138,189,213,8,94,137,135,97,251,33,40,199,117,136,142]},"announce":[],"urlList":[]}}