{"title":"The.Gate.DVDRip.Xvid.1987-tots","uid":4480701,"size":736747366,"categoryP":"video","categoryS":"movies","magnet":"?xt=urn:btih:2d507403ce556fe682e17a34f4f814ca3fcee743&amp;dn=The.Gate.DVDRip.Xvid.1987-tots&amp;tr=udp%3A%2F%2Ftracker.openbittorrent.com%3A80&amp;tr=udp%3A%2F%2Fopen.demonii.com%3A1337&amp;tr=udp%3A%2F%2Ftracker.coppersurfer.tk%3A6969&amp;tr=udp%3A%2F%2Fexodus.desync.com%3A6969","seeders":1,"leechers":0,"uploader":"Shalashaska1","files":1,"time":1225556659,"description":"Three young children accidentally release a horde of nasty, pint-sized demons from a hole in a suburban backyard... \n\n\n\n&quot;XVID&quot; (XviD Mpeg-4 Video)\n624x476, 29.970030 fps\n\n\n192 kbps (MPEG-1 Layer-3 Audio (mp3))\n2 channels, 48000Hz\n\n\n\nEnjoy....","torrent":{"xt":"urn:btih:2d507403ce556fe682e17a34f4f814ca3fcee743","amp;dn":"The.Gate.DVDRip.Xvid.1987-tots","amp;tr":["udp%3A%2F%2Ftracker.openbittorrent.com%3A80","udp%3A%2F%2Fopen.demonii.com%3A1337","udp%3A%2F%2Ftracker.coppersurfer.tk%3A6969","udp%3A%2F%2Fexodus.desync.com%3A6969"],"infoHash":"2d507403ce556fe682e17a34f4f814ca3fcee743","infoHashBuffer":{"type":"Buffer","data":[45,80,116,3,206,85,111,230,130,225,122,52,244,248,20,202,63,206,231,67]},"announce":[],"urlList":[]}}