{"title":"Dvd ripper for mac (intel and ppc versions) serial included","uid":4229566,"size":13252571,"categoryP":"applications","categoryS":"mac","magnet":"?xt=urn:btih:3431d99727b127f500dcc99bc5471457b3d554cc&amp;dn=Dvd+ripper+for+mac+%28intel+and+ppc+versions%29+serial+included&amp;tr=udp%3A%2F%2Ftracker.openbittorrent.com%3A80&amp;tr=udp%3A%2F%2Fopen.demonii.com%3A1337&amp;tr=udp%3A%2F%2Ftracker.coppersurfer.tk%3A6969&amp;tr=udp%3A%2F%2Fexodus.desync.com%3A6969","seeders":1,"leechers":0,"uploader":"gerit","files":1,"time":1212977915,"description":"DVD ripper for mac  includes both version  Intel and PPC.\n\n\nserial included\n\nthis is the latest version.\n\nDVD ripper 4.0","torrent":{"xt":"urn:btih:3431d99727b127f500dcc99bc5471457b3d554cc","amp;dn":"Dvd+ripper+for+mac+%28intel+and+ppc+versions%29+serial+included","amp;tr":["udp%3A%2F%2Ftracker.openbittorrent.com%3A80","udp%3A%2F%2Fopen.demonii.com%3A1337","udp%3A%2F%2Ftracker.coppersurfer.tk%3A6969","udp%3A%2F%2Fexodus.desync.com%3A6969"],"infoHash":"3431d99727b127f500dcc99bc5471457b3d554cc","infoHashBuffer":{"type":"Buffer","data":[52,49,217,151,39,177,39,245,0,220,201,155,197,71,20,87,179,213,84,204]},"announce":[],"urlList":[]}}