{"title":"Moms In Control - Ashley Downs, Baby Jewel [720p]","uid":14037429,"size":2006037958,"categoryP":"porn","categoryS":"movie_clips","magnet":"?xt=urn:btih:4375cc4d10edabc705365602bad605a4dfb727d5&amp;dn=Moms+In+Control+-+Ashley+Downs%2C+Baby+Jewel+%5B720p%5D&amp;tr=udp%3A%2F%2Ftracker.leechers-paradise.org%3A6969&amp;tr=udp%3A%2F%2Fzer0day.ch%3A1337&amp;tr=udp%3A%2F%2Fopen.demonii.com%3A1337&amp;tr=udp%3A%2F%2Ftracker.coppersurfer.tk%3A6969&amp;tr=udp%3A%2F%2Fexodus.desync.com%3A6969","seeders":1,"leechers":2,"uploader":"hunter534","files":1,"time":1458982497,"description":"Baby and her boyfriend Jordi are ready to fool around after school, but Baby's slutty stepmom Ashley is home. She doesn't want Baby fucking her boyfriend so she makes her stepdaughter leave her bedroom door open while the young couple &quot;studies.&quot; Baby doesn't care, she's going to fuck Jordi anyway! What she doesn't realize is how badly Ashley wants Jordi's dick for herself.\r\n\r\nSize: 1.87 GiB\r\nTime: 00:31:50\r\nFormat:MP4\r\nGenre: Uniform, MILF, Natural Tits, Huge Tits, Blonde, Brunette, Threesome, Wife, School Girl, Girlfriend, Stepmom, Cheating, Big Tits\r\n\r\nCOVER+SCEENSHOT:\r\n \nhttp://photo-up.info/img-56f64030ec667.html \r\n \nhttp://photo-up.info/img-56f6403d17201.html","torrent":{"xt":"urn:btih:4375cc4d10edabc705365602bad605a4dfb727d5","amp;dn":"Moms+In+Control+-+Ashley+Downs%2C+Baby+Jewel+%5B720p%5D","amp;tr":["udp%3A%2F%2Ftracker.leechers-paradise.org%3A6969","udp%3A%2F%2Fzer0day.ch%3A1337","udp%3A%2F%2Fopen.demonii.com%3A1337","udp%3A%2F%2Ftracker.coppersurfer.tk%3A6969","udp%3A%2F%2Fexodus.desync.com%3A6969"],"infoHash":"4375cc4d10edabc705365602bad605a4dfb727d5","infoHashBuffer":{"type":"Buffer","data":[67,117,204,77,16,237,171,199,5,54,86,2,186,214,5,164,223,183,39,213]},"announce":[],"urlList":[]}}