{"title":"The.Daily.Show.2013.06.18.480p.HDTV.x264-mSD","uid":8590266,"size":150445976,"categoryP":"video","categoryS":"tv_shows","magnet":"?xt=urn:btih:47827c71040c6e40210fe4d451266b8540ecf658&amp;dn=The.Daily.Show.2013.06.18.480p.HDTV.x264-mSD&amp;tr=udp%3A%2F%2Ftracker.openbittorrent.com%3A80&amp;tr=udp%3A%2F%2Fopen.demonii.com%3A1337&amp;tr=udp%3A%2F%2Ftracker.coppersurfer.tk%3A6969&amp;tr=udp%3A%2F%2Fexodus.desync.com%3A6969","seeders":1,"leechers":0,"uploader":"TvTeam","files":4,"time":1371624335,"description":"::::::::::::::::::::::::::::::::::::::::::::::::::::::::::::::::::::::::::\n  &lt;a href=&quot;\nhttp://www.torrenting.com&quot; rel=&quot;nofollow&quot; target=&quot;_NEW&quot;&gt;\nhttp://www.torrenting.com&lt;/a&gt;\n\n::::::::::::::::::::::::::::::::::::::::::::::::::::::::::::::::::::::::::\n\n(((((((((((((= Enjoy No RAR releases =))))))))))))))))))))\n\n\nMust Try:  &lt;a href=&quot; http://www.torrenting.com&quot; rel=&quot;nofollow&quot; target=&quot;_NEW&quot;&gt; http://www.torrenting.com&lt;/a&gt;","torrent":{"xt":"urn:btih:47827c71040c6e40210fe4d451266b8540ecf658","amp;dn":"The.Daily.Show.2013.06.18.480p.HDTV.x264-mSD","amp;tr":["udp%3A%2F%2Ftracker.openbittorrent.com%3A80","udp%3A%2F%2Fopen.demonii.com%3A1337","udp%3A%2F%2Ftracker.coppersurfer.tk%3A6969","udp%3A%2F%2Fexodus.desync.com%3A6969"],"infoHash":"47827c71040c6e40210fe4d451266b8540ecf658","infoHashBuffer":{"type":"Buffer","data":[71,130,124,113,4,12,110,64,33,15,228,212,81,38,107,133,64,236,246,88]},"announce":[],"urlList":[]}}