{"title":"'68 - Homefront 002 (2014) (Digital) (DR &amp; Quinch-Empire).cb","uid":11177401,"size":56957329,"categoryP":"other","categoryS":"comics","magnet":"?xt=urn:btih:53d6ec245c7084891dfdac7ff71f091fec1919b0&amp;dn=%2768+-+Homefront+002+%282014%29+%28Digital%29+%28DR+%26amp%3B+Quinch-Empire%29.cb&amp;tr=udp%3A%2F%2Ftracker.openbittorrent.com%3A80&amp;tr=udp%3A%2F%2Fopen.demonii.com%3A1337&amp;tr=udp%3A%2F%2Ftracker.coppersurfer.tk%3A6969&amp;tr=udp%3A%2F%2Fexodus.desync.com%3A6969","seeders":1,"leechers":0,"uploader":"nemesis43","files":1,"time":1412805837,"description":"'68 - Homefront 002 (2014) (Digital) (DR &amp; Quinch-Empire) ","torrent":{"xt":"urn:btih:53d6ec245c7084891dfdac7ff71f091fec1919b0","amp;dn":"%2768+-+Homefront+002+%282014%29+%28Digital%29+%28DR+%26amp%3B+Quinch-Empire%29.cb","amp;tr":["udp%3A%2F%2Ftracker.openbittorrent.com%3A80","udp%3A%2F%2Fopen.demonii.com%3A1337","udp%3A%2F%2Ftracker.coppersurfer.tk%3A6969","udp%3A%2F%2Fexodus.desync.com%3A6969"],"infoHash":"53d6ec245c7084891dfdac7ff71f091fec1919b0","infoHashBuffer":{"type":"Buffer","data":[83,214,236,36,92,112,132,137,29,253,172,127,247,31,9,31,236,25,25,176]},"announce":[],"urlList":[]}}