{"title":"Pervcity Anna Bell Peaks Stunning Big","uid":14901949,"size":123020731,"categoryP":"porn","categoryS":"movie_clips","magnet":"?xt=urn:btih:5773a2ad867ea5a28767c4f728b327dcd7f8376a&amp;dn=Pervcity+Anna+Bell+Peaks+Stunning+Big&amp;tr=udp%3A%2F%2Ftracker.leechers-paradise.org%3A6969&amp;tr=udp%3A%2F%2Fzer0day.ch%3A1337&amp;tr=udp%3A%2F%2Fopen.demonii.com%3A1337&amp;tr=udp%3A%2F%2Ftracker.coppersurfer.tk%3A6969&amp;tr=udp%3A%2F%2Fexodus.desync.com%3A6969","seeders":1,"leechers":0,"uploader":"demonoidt","files":1,"time":1465829396,"description":"Samples\r\n \nhttp://adultwallpapers.co.in/pervcity-anna-bell-peaks-stunning-big/\r\n \nhttp://demonoid.co/2016/06/13/pervcity-anna-bell-peaks-stunning-big/","torrent":{"xt":"urn:btih:5773a2ad867ea5a28767c4f728b327dcd7f8376a","amp;dn":"Pervcity+Anna+Bell+Peaks+Stunning+Big","amp;tr":["udp%3A%2F%2Ftracker.leechers-paradise.org%3A6969","udp%3A%2F%2Fzer0day.ch%3A1337","udp%3A%2F%2Fopen.demonii.com%3A1337","udp%3A%2F%2Ftracker.coppersurfer.tk%3A6969","udp%3A%2F%2Fexodus.desync.com%3A6969"],"infoHash":"5773a2ad867ea5a28767c4f728b327dcd7f8376a","infoHashBuffer":{"type":"Buffer","data":[87,115,162,173,134,126,165,162,135,103,196,247,40,179,39,220,215,248,55,106]},"announce":[],"urlList":[]}}