{"title":"Sato Goldschlag - Mr. Mister (feat. Wynter Gordon) {2012-Single}","uid":7176885,"size":14021711,"categoryP":"audio","categoryS":"music","magnet":"?xt=urn:btih:584324dad90162d85cfc9cd4ce26366a9e150ae8&amp;dn=Sato+Goldschlag+-+Mr.+Mister+%28feat.+Wynter+Gordon%29+%7B2012-Single%7D&amp;tr=udp%3A%2F%2Ftracker.openbittorrent.com%3A80&amp;tr=udp%3A%2F%2Fopen.demonii.com%3A1337&amp;tr=udp%3A%2F%2Ftracker.coppersurfer.tk%3A6969&amp;tr=udp%3A%2F%2Fexodus.desync.com%3A6969","seeders":1,"leechers":0,"uploader":"NishLakhani","files":-1,"time":1334142422,"description":"320 kbps!!\n\niTunes Ripped!!\n\nRipped By NL!!\n\nPlease Seed,Comment And Rate On Quality!!\n\nThanx :)\n\nHaters Never Die,\n\nThey Fuckin' Multiply!!\t","torrent":{"xt":"urn:btih:584324dad90162d85cfc9cd4ce26366a9e150ae8","amp;dn":"Sato+Goldschlag+-+Mr.+Mister+%28feat.+Wynter+Gordon%29+%7B2012-Single%7D","amp;tr":["udp%3A%2F%2Ftracker.openbittorrent.com%3A80","udp%3A%2F%2Fopen.demonii.com%3A1337","udp%3A%2F%2Ftracker.coppersurfer.tk%3A6969","udp%3A%2F%2Fexodus.desync.com%3A6969"],"infoHash":"584324dad90162d85cfc9cd4ce26366a9e150ae8","infoHashBuffer":{"type":"Buffer","data":[88,67,36,218,217,1,98,216,92,252,156,212,206,38,54,106,158,21,10,232]},"announce":[],"urlList":[]}}