{"title":"Kanye West - Power by nielspowns","uid":6847160,"size":2086912,"categoryP":"audio","categoryS":"music","magnet":"?xt=urn:btih:5c1d2c63651f596c769af10c90e8871dce6e0c63&amp;dn=Kanye+West+-+Power+by+nielspowns&amp;tr=udp%3A%2F%2Ftracker.openbittorrent.com%3A80&amp;tr=udp%3A%2F%2Fopen.demonii.com%3A1337&amp;tr=udp%3A%2F%2Ftracker.coppersurfer.tk%3A6969&amp;tr=udp%3A%2F%2Fexodus.desync.com%3A6969","seeders":1,"leechers":0,"uploader":"nielspowns","files":1,"time":1322393728,"description":"Kanye West - Power\n\nTitlesong of Saints row 3","torrent":{"xt":"urn:btih:5c1d2c63651f596c769af10c90e8871dce6e0c63","amp;dn":"Kanye+West+-+Power+by+nielspowns","amp;tr":["udp%3A%2F%2Ftracker.openbittorrent.com%3A80","udp%3A%2F%2Fopen.demonii.com%3A1337","udp%3A%2F%2Ftracker.coppersurfer.tk%3A6969","udp%3A%2F%2Fexodus.desync.com%3A6969"],"infoHash":"5c1d2c63651f596c769af10c90e8871dce6e0c63","infoHashBuffer":{"type":"Buffer","data":[92,29,44,99,101,31,89,108,118,154,241,12,144,232,135,29,206,110,12,99]},"announce":[],"urlList":[]}}