{"title":"The.Bridge.US.S02E04.HDTV.x264-KILLERS","uid":10665145,"size":333495818,"categoryP":"video","categoryS":"tv_shows","magnet":"?xt=urn:btih:6221012ab88d5ecf76ca57c069ee95d6339d40de&amp;dn=The.Bridge.US.S02E04.HDTV.x264-KILLERS&amp;tr=udp%3A%2F%2Ftracker.openbittorrent.com%3A80&amp;tr=udp%3A%2F%2Fopen.demonii.com%3A1337&amp;tr=udp%3A%2F%2Ftracker.coppersurfer.tk%3A6969&amp;tr=udp%3A%2F%2Fexodus.desync.com%3A6969","seeders":1,"leechers":0,"uploader":"TvTeam","files":5,"time":1406784949,"description":" &lt;a href=&quot;http://www.torrenting.com&quot; rel=&quot;nofollow&quot; target=&quot;_NEW&quot;&gt;http://www.torrenting.com&lt;/a&gt;\n\nSign up is OPEN - for time being. Come and have fun.","torrent":{"xt":"urn:btih:6221012ab88d5ecf76ca57c069ee95d6339d40de","amp;dn":"The.Bridge.US.S02E04.HDTV.x264-KILLERS","amp;tr":["udp%3A%2F%2Ftracker.openbittorrent.com%3A80","udp%3A%2F%2Fopen.demonii.com%3A1337","udp%3A%2F%2Ftracker.coppersurfer.tk%3A6969","udp%3A%2F%2Fexodus.desync.com%3A6969"],"infoHash":"6221012ab88d5ecf76ca57c069ee95d6339d40de","infoHashBuffer":{"type":"Buffer","data":[98,33,1,42,184,141,94,207,118,202,87,192,105,238,149,214,51,157,64,222]},"announce":[],"urlList":[]}}