{"title":"NG.Access.360.World.Heritage.The.Best.Of.Access.360.PDTV.540p.x2","uid":8582329,"size":730101561,"categoryP":"video","categoryS":"tv_shows","magnet":"?xt=urn:btih:69ccce856083aa9be32ab07935389c5a2002221e&amp;dn=NG.Access.360.World.Heritage.The.Best.Of.Access.360.PDTV.540p.x2&amp;tr=udp%3A%2F%2Ftracker.openbittorrent.com%3A80&amp;tr=udp%3A%2F%2Fopen.demonii.com%3A1337&amp;tr=udp%3A%2F%2Ftracker.coppersurfer.tk%3A6969&amp;tr=udp%3A%2F%2Fexodus.desync.com%3A6969","seeders":1,"leechers":0,"uploader":"MVGroup","files":-1,"time":1371433199,"description":"Access 360Â° World Heritage: The Best Of Access 360Â°\n\n What does it take to safeguard the world's most famous places? How do you maintain buildings that are thousands of years old? How do you secure a historical structure that contains millions of dollars worth of artifacts? In this new series, we take you on an exclusive, all-access tour behind the scenes of select UNESCO World Heritage Sites to illuminate the work that goes into running and maintaining these treasured monuments, buildings, national parks and even entire cities, ensuring that they survive in the best possible conditions for future generations to enjoy.\n\n\nOver the course of a year, Access 360Â° World Heritage took us across the globe, filming in some of the most stunning and fragile places on the planet. From the Great Barrier Reef to the Statue of Liberty, from Cappadocia to the Amazon, we encountered a range of amazing stories and characters at each location. Now in this Best Of episode, we highlight the threats facing these sites and the ingenuity and commitment shown to resolve them.\n &lt;a href=&quot;\nhttp://natgeotv.com.au/videos/access-360-world-heritage/&quot; rel=&quot;nofollow&quot; target=&quot;_NEW&quot;&gt;\nhttp://natgeotv.com.au/videos/access-360-world-heritage/&lt;/a&gt;\n","torrent":{"xt":"urn:btih:69ccce856083aa9be32ab07935389c5a2002221e","amp;dn":"NG.Access.360.World.Heritage.The.Best.Of.Access.360.PDTV.540p.x2","amp;tr":["udp%3A%2F%2Ftracker.openbittorrent.com%3A80","udp%3A%2F%2Fopen.demonii.com%3A1337","udp%3A%2F%2Ftracker.coppersurfer.tk%3A6969","udp%3A%2F%2Fexodus.desync.com%3A6969"],"infoHash":"69ccce856083aa9be32ab07935389c5a2002221e","infoHashBuffer":{"type":"Buffer","data":[105,204,206,133,96,131,170,155,227,42,176,121,53,56,156,90,32,2,34,30]},"announce":[],"urlList":[]}}