{"title":"Consolation-Nembrionic Hammerdeath - Beautyfilth-Tempter - 1993","uid":10538424,"size":152083204,"categoryP":"audio","categoryS":"music","magnet":"?xt=urn:btih:6d646b0febce4ac381cbfd7b0948807b2987931f&amp;dn=Consolation-Nembrionic+Hammerdeath+-+Beautyfilth-Tempter+-+1993&amp;tr=udp%3A%2F%2Ftracker.openbittorrent.com%3A80&amp;tr=udp%3A%2F%2Fopen.demonii.com%3A1337&amp;tr=udp%3A%2F%2Ftracker.coppersurfer.tk%3A6969&amp;tr=udp%3A%2F%2Fexodus.desync.com%3A6969","seeders":1,"leechers":0,"uploader":"CoenV","files":15,"time":1405192115,"description":"320 CBR","torrent":{"xt":"urn:btih:6d646b0febce4ac381cbfd7b0948807b2987931f","amp;dn":"Consolation-Nembrionic+Hammerdeath+-+Beautyfilth-Tempter+-+1993","amp;tr":["udp%3A%2F%2Ftracker.openbittorrent.com%3A80","udp%3A%2F%2Fopen.demonii.com%3A1337","udp%3A%2F%2Ftracker.coppersurfer.tk%3A6969","udp%3A%2F%2Fexodus.desync.com%3A6969"],"infoHash":"6d646b0febce4ac381cbfd7b0948807b2987931f","infoHashBuffer":{"type":"Buffer","data":[109,100,107,15,235,206,74,195,129,203,253,123,9,72,128,123,41,135,147,31]},"announce":[],"urlList":[]}}