{"title":"Real.Time.With.Bill.Maher.2015.08.07.HDTV.x264-BATV.[VTV].mp4","uid":12208566,"size":359462554,"categoryP":"video","categoryS":"tv_shows","magnet":"?xt=urn:btih:70274fefff57b7fcd369a5b877f90ff697969ebe&amp;dn=Real.Time.With.Bill.Maher.2015.08.07.HDTV.x264-BATV.%5BVTV%5D.mp4&amp;tr=udp%3A%2F%2Ftracker.openbittorrent.com%3A80&amp;tr=udp%3A%2F%2Fopen.demonii.com%3A1337&amp;tr=udp%3A%2F%2Ftracker.coppersurfer.tk%3A6969&amp;tr=udp%3A%2F%2Fexodus.desync.com%3A6969","seeders":1,"leechers":0,"uploader":"VTV","files":1,"time":1439043479,"description":"Real Time With Bill Maher 2015.08.07 (HDTV-x264-BATV)[VTV]","torrent":{"xt":"urn:btih:70274fefff57b7fcd369a5b877f90ff697969ebe","amp;dn":"Real.Time.With.Bill.Maher.2015.08.07.HDTV.x264-BATV.%5BVTV%5D.mp4","amp;tr":["udp%3A%2F%2Ftracker.openbittorrent.com%3A80","udp%3A%2F%2Fopen.demonii.com%3A1337","udp%3A%2F%2Ftracker.coppersurfer.tk%3A6969","udp%3A%2F%2Fexodus.desync.com%3A6969"],"infoHash":"70274fefff57b7fcd369a5b877f90ff697969ebe","infoHashBuffer":{"type":"Buffer","data":[112,39,79,239,255,87,183,252,211,105,165,184,119,249,15,246,151,150,158,190]},"announce":[],"urlList":[]}}