{"title":"[FFF] Witch Craft Works - 08 [BDA7D046].mkv","uid":9700537,"size":520920373,"categoryP":"video","categoryS":"hd___tv_shows","magnet":"?xt=urn:btih:76f7e23d23cc44350d53df560ba64f534f5ec78d&amp;dn=%5BFFF%5D+Witch+Craft+Works+-+08+%5BBDA7D046%5D.mkv&amp;tr=udp%3A%2F%2Ftracker.openbittorrent.com%3A80&amp;tr=udp%3A%2F%2Fopen.demonii.com%3A1337&amp;tr=udp%3A%2F%2Ftracker.coppersurfer.tk%3A6969&amp;tr=udp%3A%2F%2Fexodus.desync.com%3A6969","seeders":1,"leechers":0,"uploader":"darkj6","files":1,"time":1393991870,"description":" ______   _______  ______    ___   _      ___  --------|\n|      | |   _   ||    _ |  |   | | |    |   ||   |----|    \n|  _    ||  |_|  ||   | ||  |   |_| |    |   ||   |___ \n| | |   ||       ||   |_||_ |      _|    |   ||    _  |\n| |_|   ||       ||    __  ||     |_  ___|   ||   | | |\n|       ||   _   ||   |  | ||    _  ||       ||   |_| |\n|______| |__| |__||___|  |_||___| |_||_______||_______|\t\n","torrent":{"xt":"urn:btih:76f7e23d23cc44350d53df560ba64f534f5ec78d","amp;dn":"%5BFFF%5D+Witch+Craft+Works+-+08+%5BBDA7D046%5D.mkv","amp;tr":["udp%3A%2F%2Ftracker.openbittorrent.com%3A80","udp%3A%2F%2Fopen.demonii.com%3A1337","udp%3A%2F%2Ftracker.coppersurfer.tk%3A6969","udp%3A%2F%2Fexodus.desync.com%3A6969"],"infoHash":"76f7e23d23cc44350d53df560ba64f534f5ec78d","infoHashBuffer":{"type":"Buffer","data":[118,247,226,61,35,204,68,53,13,83,223,86,11,166,79,83,79,94,199,141]},"announce":[],"urlList":[]}}