{"title":"NBA.2013.RS.(25 nov).PHX.Suns.v.MIA.Heat.720p.60fps","uid":9253566,"size":3693212718,"categoryP":"video","categoryS":"hd___tv_shows","magnet":"?xt=urn:btih:7766457bb04c78c48940ea38c1f8e7a1fc9c3369&amp;dn=NBA.2013.RS.%2825+nov%29.PHX.Suns.v.MIA.Heat.720p.60fps&amp;tr=udp%3A%2F%2Ftracker.openbittorrent.com%3A80&amp;tr=udp%3A%2F%2Fopen.demonii.com%3A1337&amp;tr=udp%3A%2F%2Ftracker.coppersurfer.tk%3A6969&amp;tr=udp%3A%2F%2Fexodus.desync.com%3A6969","seeders":1,"leechers":0,"uploader":"Nepotu","files":1,"time":1385508332,"description":"Credit: m4rtyr","torrent":{"xt":"urn:btih:7766457bb04c78c48940ea38c1f8e7a1fc9c3369","amp;dn":"NBA.2013.RS.%2825+nov%29.PHX.Suns.v.MIA.Heat.720p.60fps","amp;tr":["udp%3A%2F%2Ftracker.openbittorrent.com%3A80","udp%3A%2F%2Fopen.demonii.com%3A1337","udp%3A%2F%2Ftracker.coppersurfer.tk%3A6969","udp%3A%2F%2Fexodus.desync.com%3A6969"],"infoHash":"7766457bb04c78c48940ea38c1f8e7a1fc9c3369","infoHashBuffer":{"type":"Buffer","data":[119,102,69,123,176,76,120,196,137,64,234,56,193,248,231,161,252,156,51,105]},"announce":[],"urlList":[]}}