{"title":"New.Girl.S05E08.1080p.HEVC.x265-MeGusta","uid":15636149,"size":261334639,"categoryP":"video","categoryS":"tv_shows","magnet":"?xt=urn:btih:783972aefb0f6518b3a6ed5c48a061e6c43bd661&amp;dn=New.Girl.S05E08.1080p.HEVC.x265-MeGusta&amp;tr=udp%3A%2F%2Ftracker.leechers-paradise.org%3A6969&amp;tr=udp%3A%2F%2Fzer0day.ch%3A1337&amp;tr=udp%3A%2F%2Fopen.demonii.com%3A1337&amp;tr=udp%3A%2F%2Ftracker.coppersurfer.tk%3A6969&amp;tr=udp%3A%2F%2Fexodus.desync.com%3A6969","seeders":1,"leechers":0,"uploader":"TvTeam","files":7,"time":1471989370,"description":"Torrent from:\r\n~~~~~~~~~~~~ \nhttps://www.torrenting.com\r\n\r\nJoin us and become part of the BIG family! Yarrrrrrrrrrrrrr!!!","torrent":{"xt":"urn:btih:783972aefb0f6518b3a6ed5c48a061e6c43bd661","amp;dn":"New.Girl.S05E08.1080p.HEVC.x265-MeGusta","amp;tr":["udp%3A%2F%2Ftracker.leechers-paradise.org%3A6969","udp%3A%2F%2Fzer0day.ch%3A1337","udp%3A%2F%2Fopen.demonii.com%3A1337","udp%3A%2F%2Ftracker.coppersurfer.tk%3A6969","udp%3A%2F%2Fexodus.desync.com%3A6969"],"infoHash":"783972aefb0f6518b3a6ed5c48a061e6c43bd661","infoHashBuffer":{"type":"Buffer","data":[120,57,114,174,251,15,101,24,179,166,237,92,72,160,97,230,196,59,214,97]},"announce":[],"urlList":[]}}