{"title":"007 Goldeneye (N64)  OST","uid":8047547,"size":156304195,"categoryP":"audio","categoryS":"music","magnet":"?xt=urn:btih:810df154f1d723fb09170a05c72b69c725a770a2&amp;dn=007+Goldeneye+%28N64%29++OST&amp;tr=udp%3A%2F%2Ftracker.openbittorrent.com%3A80&amp;tr=udp%3A%2F%2Fopen.demonii.com%3A1337&amp;tr=udp%3A%2F%2Ftracker.coppersurfer.tk%3A6969&amp;tr=udp%3A%2F%2Fexodus.desync.com%3A6969","seeders":1,"leechers":0,"uploader":"Th3L00nYm00N","files":58,"time":1358785819,"description":"OST for the hit game 007 Goldeneye incudes all tracks plus many bonus tracks that were not included in the game\n\nPlease remember to seed :)","torrent":{"xt":"urn:btih:810df154f1d723fb09170a05c72b69c725a770a2","amp;dn":"007+Goldeneye+%28N64%29++OST","amp;tr":["udp%3A%2F%2Ftracker.openbittorrent.com%3A80","udp%3A%2F%2Fopen.demonii.com%3A1337","udp%3A%2F%2Ftracker.coppersurfer.tk%3A6969","udp%3A%2F%2Fexodus.desync.com%3A6969"],"infoHash":"810df154f1d723fb09170a05c72b69c725a770a2","infoHashBuffer":{"type":"Buffer","data":[129,13,241,84,241,215,35,251,9,23,10,5,199,43,105,199,37,167,112,162]},"announce":[],"urlList":[]}}