{"title":"De Vliegende Panters - Hype.DUTCH","uid":4231868,"size":103251240,"categoryP":"audio","categoryS":"other","magnet":"?xt=urn:btih:84fa3e0f7bdf3fafa70cc861e986e8d70514f5c2&amp;dn=De+Vliegende+Panters+-+Hype.DUTCH&amp;tr=udp%3A%2F%2Ftracker.openbittorrent.com%3A80&amp;tr=udp%3A%2F%2Fopen.demonii.com%3A1337&amp;tr=udp%3A%2F%2Ftracker.coppersurfer.tk%3A6969&amp;tr=udp%3A%2F%2Fexodus.desync.com%3A6969","seeders":1,"leechers":1,"uploader":"vehpol","files":31,"time":1213097248,"description":"Het is weer tijd voor een paar cabaret CD&amp;#039;s, beginnende met; De Vliegende Panters - Hype.\n\nAantal CD&amp;#039;s: 2\nLengte CD1: 43min\nLengte CD2: 47min\nJaar: 2000\nAudio: MP3\nBitrate: 160kbps\n\nWederom: Veel plezier ermee!","torrent":{"xt":"urn:btih:84fa3e0f7bdf3fafa70cc861e986e8d70514f5c2","amp;dn":"De+Vliegende+Panters+-+Hype.DUTCH","amp;tr":["udp%3A%2F%2Ftracker.openbittorrent.com%3A80","udp%3A%2F%2Fopen.demonii.com%3A1337","udp%3A%2F%2Ftracker.coppersurfer.tk%3A6969","udp%3A%2F%2Fexodus.desync.com%3A6969"],"infoHash":"84fa3e0f7bdf3fafa70cc861e986e8d70514f5c2","infoHashBuffer":{"type":"Buffer","data":[132,250,62,15,123,223,63,175,167,12,200,97,233,134,232,215,5,20,245,194]},"announce":[],"urlList":[]}}