{"title":"Sprawdziany Gimnazjum","uid":9697462,"size":408146049,"categoryP":"other","categoryS":"e_books","magnet":"?xt=urn:btih:9b6011bbf36654608bf0c008014d8ae61a8b916f&amp;dn=Sprawdziany+Gimnazjum&amp;tr=udp%3A%2F%2Ftracker.openbittorrent.com%3A80&amp;tr=udp%3A%2F%2Fopen.demonii.com%3A1337&amp;tr=udp%3A%2F%2Ftracker.coppersurfer.tk%3A6969&amp;tr=udp%3A%2F%2Fexodus.desync.com%3A6969","seeders":1,"leechers":0,"uploader":"Vulwsztyn","files":330,"time":1393955512,"description":"Sprawdziany Gimnazjum\nKsiÄ…Å¼ki:\nAngielski:\n-Bingo\n-Challenges\n-Connections\n-Friends\n-Inspiration\n-Longman Korepetytorium\n-Snapshot\n-Upbeat\n-Winners\nBiologia:\n-Puls Å»ycia\n-Åšwiat Biologii\nChemia:\n-KsiÄ…Å¼ka Nowej Ery (nie znam nazwy)\nGeografia:\n-Planeta\n-Puls Ziemi\nHistoria:\n-Åšladami PrzeszÅ‚oÅ›ci\nMatematyka:\n-Matematyka z Plusem\n\nNie sÄ… to wszystkie sprawdziany, ale te zdoÅ‚aÅ‚em zdobyÄ‡.\nJeÅ¼eli chcesz zasiliÄ‡ mojÄ… &quot;kolekcjÄ™&quot; pisz na e-mail:","torrent":{"xt":"urn:btih:9b6011bbf36654608bf0c008014d8ae61a8b916f","amp;dn":"Sprawdziany+Gimnazjum","amp;tr":["udp%3A%2F%2Ftracker.openbittorrent.com%3A80","udp%3A%2F%2Fopen.demonii.com%3A1337","udp%3A%2F%2Ftracker.coppersurfer.tk%3A6969","udp%3A%2F%2Fexodus.desync.com%3A6969"],"infoHash":"9b6011bbf36654608bf0c008014d8ae61a8b916f","infoHashBuffer":{"type":"Buffer","data":[155,96,17,187,243,102,84,96,139,240,192,8,1,77,138,230,26,139,145,111]},"announce":[],"urlList":[]}}