{"title":"FootFetishDaily.14.06.30.Meet.Onyx.XXX.iMAGESET-YAPG","uid":10459575,"size":85710023,"categoryP":"porn","categoryS":"other","magnet":"?xt=urn:btih:acda0516c00c058a5108c09db14fcbff11eb97df&amp;dn=FootFetishDaily.14.06.30.Meet.Onyx.XXX.iMAGESET-YAPG&amp;tr=udp%3A%2F%2Ftracker.openbittorrent.com%3A80&amp;tr=udp%3A%2F%2Fopen.demonii.com%3A1337&amp;tr=udp%3A%2F%2Ftracker.coppersurfer.tk%3A6969&amp;tr=udp%3A%2F%2Fexodus.desync.com%3A6969","seeders":1,"leechers":0,"uploader":"Drarbg","files":133,"time":1404119757,"description":" &lt;a href=&quot;https://rarbg.com&quot; rel=&quot;nofollow&quot; target=&quot;_NEW&quot;&gt;https://rarbg.com&lt;/a&gt;\n\nFootFetishDaily.com_14.06.30.Meet.Onyx.XXX.iMAGESET-YAPG\n","torrent":{"xt":"urn:btih:acda0516c00c058a5108c09db14fcbff11eb97df","amp;dn":"FootFetishDaily.14.06.30.Meet.Onyx.XXX.iMAGESET-YAPG","amp;tr":["udp%3A%2F%2Ftracker.openbittorrent.com%3A80","udp%3A%2F%2Fopen.demonii.com%3A1337","udp%3A%2F%2Ftracker.coppersurfer.tk%3A6969","udp%3A%2F%2Fexodus.desync.com%3A6969"],"infoHash":"acda0516c00c058a5108c09db14fcbff11eb97df","infoHashBuffer":{"type":"Buffer","data":[172,218,5,22,192,12,5,138,81,8,192,157,177,79,203,255,17,235,151,223]},"announce":[],"urlList":[]}}