{"title":"160 Amazing Lions HD Wallpapers 1600 X 1200 px","uid":10255038,"size":101699896,"categoryP":"other","categoryS":"pictures","magnet":"?xt=urn:btih:ad1ee7ae5b9763eccd033be30e8483c22fa6e4b6&amp;dn=160+Amazing+Lions+HD+Wallpapers+1600+X+1200+px&amp;tr=udp%3A%2F%2Ftracker.openbittorrent.com%3A80&amp;tr=udp%3A%2F%2Fopen.demonii.com%3A1337&amp;tr=udp%3A%2F%2Ftracker.coppersurfer.tk%3A6969&amp;tr=udp%3A%2F%2Fexodus.desync.com%3A6969","seeders":1,"leechers":0,"uploader":"nico1899","files":2,"time":1401399039,"description":"160 Amazing Lions HD Wallpapers 1600 X 1200 px\n\n160 JPG | 1600 X 1200 Px | 96.9 Mb\n\n======================================================\nPREVIEW:\n &lt;a href=&quot;\nhttp://imgprix.com/lions/amazing-lion-120&quot; rel=&quot;nofollow&quot; target=&quot;_NEW&quot;&gt;\nhttp://imgprix.com/lions/amazing-lion-120&lt;/a&gt; &lt;a href=&quot;\nhttp://imgprix.com/lions/amazing-lion-118&quot; rel=&quot;nofollow&quot; target=&quot;_NEW&quot;&gt;\nhttp://imgprix.com/lions/amazing-lion-118&lt;/a&gt; &lt;a href=&quot;\nhttp://imgprix.com/lions/amazing-lion-146&quot; rel=&quot;nofollow&quot; target=&quot;_NEW&quot;&gt;\nhttp://imgprix.com/lions/amazing-lion-146&lt;/a&gt; &lt;a href=&quot;\nhttp://imgprix.com/lions/amazing-lion-82&quot; rel=&quot;nofollow&quot; target=&quot;_NEW&quot;&gt;\nhttp://imgprix.com/lions/amazing-lion-82&lt;/a&gt;\n\n======================================================","torrent":{"xt":"urn:btih:ad1ee7ae5b9763eccd033be30e8483c22fa6e4b6","amp;dn":"160+Amazing+Lions+HD+Wallpapers+1600+X+1200+px","amp;tr":["udp%3A%2F%2Ftracker.openbittorrent.com%3A80","udp%3A%2F%2Fopen.demonii.com%3A1337","udp%3A%2F%2Ftracker.coppersurfer.tk%3A6969","udp%3A%2F%2Fexodus.desync.com%3A6969"],"infoHash":"ad1ee7ae5b9763eccd033be30e8483c22fa6e4b6","infoHashBuffer":{"type":"Buffer","data":[173,30,231,174,91,151,99,236,205,3,59,227,14,132,131,194,47,166,228,182]},"announce":[],"urlList":[]}}