{"title":"Rush Limbaugh - Tuesday, January 21, 2014 MP3 not CF","uid":9508029,"size":70625000,"categoryP":"audio","categoryS":"other","magnet":"?xt=urn:btih:b03923a5f61982f8cae0a4cc625e86e0f6287958&amp;dn=Rush+Limbaugh+-+Tuesday%2C+January+21%2C+2014+MP3+not+CF&amp;tr=udp%3A%2F%2Ftracker.openbittorrent.com%3A80&amp;tr=udp%3A%2F%2Fopen.demonii.com%3A1337&amp;tr=udp%3A%2F%2Ftracker.coppersurfer.tk%3A6969&amp;tr=udp%3A%2F%2Fexodus.desync.com%3A6969","seeders":1,"leechers":0,"uploader":"amuck5","files":6,"time":1390350664,"description":"Rush Limbaugh - Tuesday, January 21, 2014 MP3 not CF\n\n\nAlternate: fenopy.se slash user slash amuck5\n","torrent":{"xt":"urn:btih:b03923a5f61982f8cae0a4cc625e86e0f6287958","amp;dn":"Rush+Limbaugh+-+Tuesday%2C+January+21%2C+2014+MP3+not+CF","amp;tr":["udp%3A%2F%2Ftracker.openbittorrent.com%3A80","udp%3A%2F%2Fopen.demonii.com%3A1337","udp%3A%2F%2Ftracker.coppersurfer.tk%3A6969","udp%3A%2F%2Fexodus.desync.com%3A6969"],"infoHash":"b03923a5f61982f8cae0a4cc625e86e0f6287958","infoHashBuffer":{"type":"Buffer","data":[176,57,35,165,246,25,130,248,202,224,164,204,98,94,134,224,246,40,121,88]},"announce":[],"urlList":[]}}