{"title":"NubileFilms.14.02.12.Tracy.Missing.You.XXX.1080p.MP4-KTR","uid":9604533,"size":669838199,"categoryP":"porn","categoryS":"other","magnet":"?xt=urn:btih:b6496be8e3cef2e3ff1d140f77b19a9b66145a0f&amp;dn=NubileFilms.14.02.12.Tracy.Missing.You.XXX.1080p.MP4-KTR&amp;tr=udp%3A%2F%2Ftracker.openbittorrent.com%3A80&amp;tr=udp%3A%2F%2Fopen.demonii.com%3A1337&amp;tr=udp%3A%2F%2Ftracker.coppersurfer.tk%3A6969&amp;tr=udp%3A%2F%2Fexodus.desync.com%3A6969","seeders":1,"leechers":0,"uploader":"Drarbg","files":3,"time":1392194107,"description":"NubileFilms.14.02.12.Tracy.Missing.You.XXX.1080p.MP4-KTR\n-----------------------------------------\nScreens : &lt;a href=&quot;\nhttp://imagecurl.org/viewer.php?file=92852371806270563513.jpg&quot; rel=&quot;nofollow&quot; target=&quot;_NEW&quot;&gt;\nhttp://imagecurl.org/viewer.php?file=92852371806270563513.jpg&lt;/a&gt;\n\n","torrent":{"xt":"urn:btih:b6496be8e3cef2e3ff1d140f77b19a9b66145a0f","amp;dn":"NubileFilms.14.02.12.Tracy.Missing.You.XXX.1080p.MP4-KTR","amp;tr":["udp%3A%2F%2Ftracker.openbittorrent.com%3A80","udp%3A%2F%2Fopen.demonii.com%3A1337","udp%3A%2F%2Ftracker.coppersurfer.tk%3A6969","udp%3A%2F%2Fexodus.desync.com%3A6969"],"infoHash":"b6496be8e3cef2e3ff1d140f77b19a9b66145a0f","infoHashBuffer":{"type":"Buffer","data":[182,73,107,232,227,206,242,227,255,29,20,15,119,177,154,155,102,20,90,15]},"announce":[],"urlList":[]}}