{"title":"Triggerfinger - Soon (acoustic) '08.mp3","uid":4543932,"size":6993353,"categoryP":"audio","categoryS":"music","magnet":"?xt=urn:btih:c84a0e72638b2a15e1a7e467852d6548da6daa3d&amp;dn=Triggerfinger+-+Soon+%28acoustic%29+%5C%2708.mp3&amp;tr=udp%3A%2F%2Ftracker.openbittorrent.com%3A80&amp;tr=udp%3A%2F%2Fopen.demonii.com%3A1337&amp;tr=udp%3A%2F%2Ftracker.coppersurfer.tk%3A6969&amp;tr=udp%3A%2F%2Fexodus.desync.com%3A6969","seeders":1,"leechers":0,"uploader":"vdcririe","files":1,"time":1228056599,"description":"You find the original version on the &quot;what grabs ya&quot; album.","torrent":{"xt":"urn:btih:c84a0e72638b2a15e1a7e467852d6548da6daa3d","amp;dn":"Triggerfinger+-+Soon+%28acoustic%29+%5C%2708.mp3","amp;tr":["udp%3A%2F%2Ftracker.openbittorrent.com%3A80","udp%3A%2F%2Fopen.demonii.com%3A1337","udp%3A%2F%2Ftracker.coppersurfer.tk%3A6969","udp%3A%2F%2Fexodus.desync.com%3A6969"],"infoHash":"c84a0e72638b2a15e1a7e467852d6548da6daa3d","infoHashBuffer":{"type":"Buffer","data":[200,74,14,114,99,139,42,21,225,167,228,103,133,45,101,72,218,109,170,61]},"announce":[],"urlList":[]}}