{"title":"Power In The Music","uid":11147966,"size":374232934,"categoryP":"audio","categoryS":"flac","magnet":"?xt=urn:btih:ccebe8f12671f145652f6f0b94b17941eeabdded&amp;dn=Power+In+The+Music&amp;tr=udp%3A%2F%2Ftracker.openbittorrent.com%3A80&amp;tr=udp%3A%2F%2Fopen.demonii.com%3A1337&amp;tr=udp%3A%2F%2Ftracker.coppersurfer.tk%3A6969&amp;tr=udp%3A%2F%2Fexodus.desync.com%3A6969","seeders":1,"leechers":0,"uploader":"orsonwellz","files":15,"time":1412288297,"description":"Talk about your unloved children!\n\nBy most accounts, &quot;Power In The Music&quot; is the most controversial of all Guess Who albums.\n\nA very small number of fans - myself among them - think that Dominic Troijano, the &quot;progressive&quot; direction of several of its compositions, the graphics and most everything else about the record are ceaselessly entertaining.\n\nMost Guess Who fans, however, think the album stinks...and can stomach nothing from the group's discography that's post-&quot;Road Food&quot;. \n\nAnd as the swell liner notes reveal, even Mr. Cummings himself has little good to say about every aspect of the disc (save &quot;Dreams,&quot; which he adores).\n\nSo be it. \n\nAnd yet...fair is fair. \n\nEvery album deserves to be heard at its best when being evaluated, and FINALLY we get to do just that with &quot;Power In The Music,&quot; thanks to the IconoClassic remastering released in 2011.\n\nIf you've already bought one or two of the grossly deficient CD versions of PITM that were previously fobbed off to an unsuspecting public, you deserve to hear this one - the one finally done right - WITHOUT shelling out more of your hard-earned.\n\nThis torrent is for you.\n","torrent":{"xt":"urn:btih:ccebe8f12671f145652f6f0b94b17941eeabdded","amp;dn":"Power+In+The+Music","amp;tr":["udp%3A%2F%2Ftracker.openbittorrent.com%3A80","udp%3A%2F%2Fopen.demonii.com%3A1337","udp%3A%2F%2Ftracker.coppersurfer.tk%3A6969","udp%3A%2F%2Fexodus.desync.com%3A6969"],"infoHash":"ccebe8f12671f145652f6f0b94b17941eeabdded","infoHashBuffer":{"type":"Buffer","data":[204,235,232,241,38,113,241,69,101,47,111,11,148,177,121,65,238,171,221,237]},"announce":[],"urlList":[]}}