{"title":"DoctorAdventures - Kagney Linn Karter (Super Nurse) NEW 27 April","uid":14450613,"size":331516960,"categoryP":"porn","categoryS":"movie_clips","magnet":"?xt=urn:btih:d11a60e3cdd1e09e19f538a43c4d048d73579599&amp;dn=DoctorAdventures+-+Kagney+Linn+Karter+%28Super+Nurse%29+NEW+27+April&amp;tr=udp%3A%2F%2Ftracker.leechers-paradise.org%3A6969&amp;tr=udp%3A%2F%2Fzer0day.ch%3A1337&amp;tr=udp%3A%2F%2Fopen.demonii.com%3A1337&amp;tr=udp%3A%2F%2Ftracker.coppersurfer.tk%3A6969&amp;tr=udp%3A%2F%2Fexodus.desync.com%3A6969","seeders":1,"leechers":0,"uploader":"xxxlavalxxx","files":2,"time":1461741893,"description":"Kagney is no ordinary nurse. Beneath her mild-mannered exterior she maintains a secret identity. She is Super Nurse, and she heals patients with her sexual know-how and wet willing pussy. When a catatonic patient like Danny D arrives, Kagney knows just what to do to rouse his spirits.\r\nCategories\r\nAnal Uniform Doctor/Nurse Bubble Butt Blonde Nurse Blowjob (POV) Big Tits\r\n \nhttp://imgdone.com/viewer.php?file=02655681892051728142.jpg\r\n \nhttp://imgdone.com/viewer.php?file=56909276390150565284.jpg","torrent":{"xt":"urn:btih:d11a60e3cdd1e09e19f538a43c4d048d73579599","amp;dn":"DoctorAdventures+-+Kagney+Linn+Karter+%28Super+Nurse%29+NEW+27+April","amp;tr":["udp%3A%2F%2Ftracker.leechers-paradise.org%3A6969","udp%3A%2F%2Fzer0day.ch%3A1337","udp%3A%2F%2Fopen.demonii.com%3A1337","udp%3A%2F%2Ftracker.coppersurfer.tk%3A6969","udp%3A%2F%2Fexodus.desync.com%3A6969"],"infoHash":"d11a60e3cdd1e09e19f538a43c4d048d73579599","infoHashBuffer":{"type":"Buffer","data":[209,26,96,227,205,209,224,158,25,245,56,164,60,77,4,141,115,87,149,153]},"announce":[],"urlList":[]}}