{"title":"sadie-jones","uid":3676350,"size":303490137,"categoryP":"porn","categoryS":"pictures","magnet":"?xt=urn:btih:d69c6b9735434ff0eaff3b74ccedfdd086d2d29b&amp;dn=sadie-jones&amp;tr=udp%3A%2F%2Ftracker.openbittorrent.com%3A80&amp;tr=udp%3A%2F%2Fopen.demonii.com%3A1337&amp;tr=udp%3A%2F%2Ftracker.coppersurfer.tk%3A6969&amp;tr=udp%3A%2F%2Fexodus.desync.com%3A6969","seeders":1,"leechers":0,"uploader":"nickster88","files":1175,"time":1177876974,"description":"For those of you who enjoyed the Sadie post, these are more sets of her not in that post.  Included:\n\n13 web galleries\n8 full sets\n3 videos\n\nCaution: A couple of sets contain topless nudity.  It didn&amp;#039;t seem like enough to place this in the Porn section.  This model is 18+.  Do not download if you do not want to see a cute topless 18yo model.\n","torrent":{"xt":"urn:btih:d69c6b9735434ff0eaff3b74ccedfdd086d2d29b","amp;dn":"sadie-jones","amp;tr":["udp%3A%2F%2Ftracker.openbittorrent.com%3A80","udp%3A%2F%2Fopen.demonii.com%3A1337","udp%3A%2F%2Ftracker.coppersurfer.tk%3A6969","udp%3A%2F%2Fexodus.desync.com%3A6969"],"infoHash":"d69c6b9735434ff0eaff3b74ccedfdd086d2d29b","infoHashBuffer":{"type":"Buffer","data":[214,156,107,151,53,67,79,240,234,255,59,116,204,237,253,208,134,210,210,155]},"announce":[],"urlList":[]}}