{"title":"Ghost.Hunters.S07E24.Distillery.of.Spirits.HDTV.XviD-tNe.avi","uid":6824121,"size":366557184,"categoryP":"video","categoryS":"tv_shows","magnet":"?xt=urn:btih:d8f5e681a56eab76501634197ca8c4b6bcdf07cb&amp;dn=Ghost.Hunters.S07E24.Distillery.of.Spirits.HDTV.XviD-tNe.avi&amp;tr=udp%3A%2F%2Ftracker.openbittorrent.com%3A80&amp;tr=udp%3A%2F%2Fopen.demonii.com%3A1337&amp;tr=udp%3A%2F%2Ftracker.coppersurfer.tk%3A6969&amp;tr=udp%3A%2F%2Fexodus.desync.com%3A6969","seeders":1,"leechers":0,"uploader":"trialNerror","files":1,"time":1321506482,"description":"Ghost Hunters - Distillery of Spirits\n \nAir Date: Nov 16, 2011\nRuntime: 00:42:59\nVideo: XviD @ 1006 Kbps\nW x H: 624 x 352 (16:9)\nFrame: 29.97 fps\nAudio: Stereo MP3\nBitrate: Variable @ 128 Kbps\nSample rate: 48.0 KHz\nAlign: On Interleaves\n \nLocated in Frankfort, Kentucky, is the oldest operating distillery in America, which is believed to be haunted by the spirit of the business' former president. For the next location the team investigates a nightclub that has had a history of violent deaths. A nightclub better known as the famous, or infamous, Bobby Mackey's Music World.","torrent":{"xt":"urn:btih:d8f5e681a56eab76501634197ca8c4b6bcdf07cb","amp;dn":"Ghost.Hunters.S07E24.Distillery.of.Spirits.HDTV.XviD-tNe.avi","amp;tr":["udp%3A%2F%2Ftracker.openbittorrent.com%3A80","udp%3A%2F%2Fopen.demonii.com%3A1337","udp%3A%2F%2Ftracker.coppersurfer.tk%3A6969","udp%3A%2F%2Fexodus.desync.com%3A6969"],"infoHash":"d8f5e681a56eab76501634197ca8c4b6bcdf07cb","infoHashBuffer":{"type":"Buffer","data":[216,245,230,129,165,110,171,118,80,22,52,25,124,168,196,182,188,223,7,203]},"announce":[],"urlList":[]}}