{"title":"Kane - Come Together (2012) DutchReleaseTeam","uid":7856311,"size":106937924,"categoryP":"audio","categoryS":"other","magnet":"?xt=urn:btih:dc9aa266dce0e3bbcbcea8e591d7ce408cd4fdc0&amp;dn=Kane+-+Come+Together+%282012%29+DutchReleaseTeam&amp;tr=udp%3A%2F%2Ftracker.openbittorrent.com%3A80&amp;tr=udp%3A%2F%2Fopen.demonii.com%3A1337&amp;tr=udp%3A%2F%2Ftracker.coppersurfer.tk%3A6969&amp;tr=udp%3A%2F%2Fexodus.desync.com%3A6969","seeders":1,"leechers":1,"uploader":"Boobin16","files":-1,"time":1353775043,"description":"Genre: Rock\n Extensie: Mp3 \n Bitrate: 320 Kbps\n Cover: Front/Back/CD\n Jaar: 2012\n\n\nTracklist\n\n 1. Under Atomic Skies \n 2. Come Together \n 3. Something Good \n 4. I Love This City \n 5. First Crash Overthrow \n 6. What Doesn't Kill You Makes You Stronger \n 7. This Is Not The End Of The World \n 8. Don't Wake Up Dead \n 9. Tracks Of Empire\n\n Deze CD wordt u aangeboden door het DutchReleaseTeam.\n Voor de reviews van de nieuwste films, muziek, series , games etc.\n Kom eens langs op   &lt;a href=&quot; http://www.hetmultimediacafe.be/&quot; rel=&quot;nofollow&quot; target=&quot;_NEW&quot;&gt; http://www.hetmultimediacafe.be/&lt;/a&gt;","torrent":{"xt":"urn:btih:dc9aa266dce0e3bbcbcea8e591d7ce408cd4fdc0","amp;dn":"Kane+-+Come+Together+%282012%29+DutchReleaseTeam","amp;tr":["udp%3A%2F%2Ftracker.openbittorrent.com%3A80","udp%3A%2F%2Fopen.demonii.com%3A1337","udp%3A%2F%2Ftracker.coppersurfer.tk%3A6969","udp%3A%2F%2Fexodus.desync.com%3A6969"],"infoHash":"dc9aa266dce0e3bbcbcea8e591d7ce408cd4fdc0","infoHashBuffer":{"type":"Buffer","data":[220,154,162,102,220,224,227,187,203,206,168,229,145,215,206,64,140,212,253,192]},"announce":[],"urlList":[]}}