{"title":"Zero Tolerance Ent Bridal Party Orgy DVDRip mp4","uid":15546294,"size":1318140388,"categoryP":"porn","categoryS":"movie_clips","magnet":"?xt=urn:btih:e1cc96d38d7d802bed4fef5715ed6f6a94ec9cf7&amp;dn=Zero+Tolerance+Ent+Bridal+Party+Orgy+DVDRip+mp4&amp;tr=udp%3A%2F%2Ftracker.leechers-paradise.org%3A6969&amp;tr=udp%3A%2F%2Fzer0day.ch%3A1337&amp;tr=udp%3A%2F%2Fopen.demonii.com%3A1337&amp;tr=udp%3A%2F%2Ftracker.coppersurfer.tk%3A6969&amp;tr=udp%3A%2F%2Fexodus.desync.com%3A6969","seeders":1,"leechers":0,"uploader":"XXX-Pack","files":1,"time":1470975287,"description":"\n Media INFO &amp; Screenshots \n \n  Duration \t:  1h 30min \n  Size \t\t:  1.23 GiB \n  WidthxHeight \t:  720x400  \n  Video Format \t:  MPEG-4  \n\n  Image Links \t:  http://imgreenshaw.com/image/X274P  \n\n  Image Links \t:  http://imgreenshaw.com/image/X2FTO  \n\n  Image Sheet \t:  http://imgreenshaw.com/image/X23t9 \n\n \t \t \t Get More Small Sized XXX Videos \n \n \t   https://thepiratebay.se/user/xxx-pack/","torrent":{"xt":"urn:btih:e1cc96d38d7d802bed4fef5715ed6f6a94ec9cf7","amp;dn":"Zero+Tolerance+Ent+Bridal+Party+Orgy+DVDRip+mp4","amp;tr":["udp%3A%2F%2Ftracker.leechers-paradise.org%3A6969","udp%3A%2F%2Fzer0day.ch%3A1337","udp%3A%2F%2Fopen.demonii.com%3A1337","udp%3A%2F%2Ftracker.coppersurfer.tk%3A6969","udp%3A%2F%2Fexodus.desync.com%3A6969"],"infoHash":"e1cc96d38d7d802bed4fef5715ed6f6a94ec9cf7","infoHashBuffer":{"type":"Buffer","data":[225,204,150,211,141,125,128,43,237,79,239,87,21,237,111,106,148,236,156,247]},"announce":[],"urlList":[]}}