{"title":"Deep Anal Drilling 4 XXX DVDRip x264-Jiggly","uid":7983286,"size":1830773751,"categoryP":"porn","categoryS":"movies","magnet":"?xt=urn:btih:efa05f6fc348558c0efc719b900b60355880378f&amp;dn=Deep+Anal+Drilling+4+XXX+DVDRip+x264-Jiggly&amp;tr=udp%3A%2F%2Ftracker.openbittorrent.com%3A80&amp;tr=udp%3A%2F%2Fopen.demonii.com%3A1337&amp;tr=udp%3A%2F%2Ftracker.coppersurfer.tk%3A6969&amp;tr=udp%3A%2F%2Fexodus.desync.com%3A6969","seeders":1,"leechers":0,"uploader":"xxxlavalxxx","files":2,"time":1357231016,"description":"Category All Sex Movies, Anal \n  \nDirector Jules Jordan \n\nStarring Lisa Ann, Jessie Rogers, Charmane Star, Melody Jordan \n\n\nDeep Anal Drilling # 4 DVD video Real Pornstars Do Anal! For the Anal Connoisseur!\n\nAmerica's top anal cop, Lisa Ann comes to set... for an anal inspection!\n\nAnal ballet dancer Melody Jordan shows off her flexibility skills... oh yeah, her asshole IS very flexible!\n\nLittle Charmane is worried about... her tight little asshole being too tight... we must intervene!\n\nDrop dead gorgeous Jessie Rogers ... gets an outdoor pussy and asshole roasting... and reaming! \n\n &lt;a href=&quot;\nhttp://www.forload.net/?v=jigglydeep.jpg&quot; rel=&quot;nofollow&quot; target=&quot;_NEW&quot;&gt;\nhttp://www.forload.net/?v=jigglydeep.jpg&lt;/a&gt;\n &lt;a href=&quot;\nhttp://www.forload.net/?v=jigglyydy.jpg&quot; rel=&quot;nofollow&quot; target=&quot;_NEW&quot;&gt;\nhttp://www.forload.net/?v=jigglyydy.jpg&lt;/a&gt;\n &lt;a href=&quot;\nhttp://www.forload.net/?v=jigglyzyz.jpg&quot; rel=&quot;nofollow&quot; target=&quot;_NEW&quot;&gt;\nhttp://www.forload.net/?v=jigglyzyz.jpg&lt;/a&gt;","torrent":{"xt":"urn:btih:efa05f6fc348558c0efc719b900b60355880378f","amp;dn":"Deep+Anal+Drilling+4+XXX+DVDRip+x264-Jiggly","amp;tr":["udp%3A%2F%2Ftracker.openbittorrent.com%3A80","udp%3A%2F%2Fopen.demonii.com%3A1337","udp%3A%2F%2Ftracker.coppersurfer.tk%3A6969","udp%3A%2F%2Fexodus.desync.com%3A6969"],"infoHash":"efa05f6fc348558c0efc719b900b60355880378f","infoHashBuffer":{"type":"Buffer","data":[239,160,95,111,195,72,85,140,14,252,113,155,144,11,96,53,88,128,55,143]},"announce":[],"urlList":[]}}