{"title":"The Dark Knight 2008 BRRip 720p x264 Illidan91 (Kingdom-Release)","uid":6471096,"size":954824689,"categoryP":"video","categoryS":"hd___movies","magnet":"?xt=urn:btih:f226c37330420451e6e18aef3414e3e77881a3bd&amp;dn=The+Dark+Knight+2008+BRRip+720p+x264+Illidan91+%28Kingdom-Release%29&amp;tr=udp%3A%2F%2Ftracker.openbittorrent.com%3A80&amp;tr=udp%3A%2F%2Fopen.demonii.com%3A1337&amp;tr=udp%3A%2F%2Ftracker.coppersurfer.tk%3A6969&amp;tr=udp%3A%2F%2Fexodus.desync.com%3A6969","seeders":1,"leechers":0,"uploader":"Illidan91","files":10,"time":1308144034,"description":"Release Title The Dark Knight 2008 BRRip 720p x264 Illidan91 (Kingdom-Release)\n\nDirected By: Christopher Nolan\n\nTagline Why So Serious\n\nCast\n\nChristian Bale ... Bruce Wayne / Batman\nHeath Ledger ... Joker\nAaron Eckhart ... Harvey Dent\nMichael Caine ... Alfred\nMaggie Gyllenhaal ... Rachel\nGary Oldman ... Gordon\nMorgan Freeman ... Lucius Fox\nMonique Gabriela Curnen ... Ramirez\nRon Dean ... Wuertz\nCillian Murphy ... Scarecrow\nChin Han ... Lau\nNestor Carbonell ... Mayor\nEric Roberts ... Maroni\nRitchie Coster ... Chechen\nAnthony Michael Hall ... Engel\n\nGenre Action|Crime|Drama\n\nLanguage English\n\nSubtitles English (SoftCoded)\n\nTotal Size 898 MB\n\nDuration 2:32:13\n\nSource The Dark Knight 2008 720p BluRay x264 ESiR ;)\n\nEncoder Illidan91\n\n\nVideo Specs\n\nContainer and Codec: MKV|AVC\nFrontend And Writing Library: x264 core 115 r1995 c1e60b9\nBitrate: 759 Kbps\nMaximum Bitrate: 40 Mbps\nEncoding: 2 Pass\nResolution: 1280 x 528\nDisplay Aspect Ratio: 2.40:1\nQuality Factor (QF): 0.047\nFrame Rate: 23.976 Fps\n\n\nAudio Specs\n\n\nAudio Codec And Type: AC3\nWriting Application: NeroAAC\nBitrate Mode: Constant\nBitrate: 64.0 Kbps\nMaximum Bitrate: 64.0 Kbps\nSample Rate: 4.1 KHz\nChannel Count: 2 Channels\n\nIMDB http://www.imdb.com/title/tt0468569/\nIMDb Rating: 8.9/10 (538,912 votes)\nTrailer http://www.imdb.com/video/screenplay/vi324468761/\nInfo Hash: F226C37330420451E6E18AEF3414E3E77881A3BD\nTrackers:\n\n\n &lt;a href=&quot;\nhttp://tpb.tracker.prq.to/announce&quot; rel=&quot;nofollow&quot; target=&quot;_NEW&quot;&gt;\nhttp://tpb.tracker.prq.to/announce&lt;/a&gt;\n\nudp://tracker.openbittorrent.com:80/announce\n &lt;a href=&quot;\nhttp://genesis.1337x.org:1337/announce&quot; rel=&quot;nofollow&quot; target=&quot;_NEW&quot;&gt;\nhttp://genesis.1337x.org:1337/announce&lt;/a&gt;\n &lt;a href=&quot;\nhttp://open.tracker.thepiratebay.se/announce&quot; rel=&quot;nofollow&quot; target=&quot;_NEW&quot;&gt;\nhttp://open.tracker.thepiratebay.se/announce&lt;/a&gt;\n &lt;a href=&quot;\nhttp://www.torrent-downloads.to:2710/announce&quot; rel=&quot;nofollow&quot; target=&quot;_NEW&quot;&gt;\nhttp://www.torrent-downloads.to:2710/announce&lt;/a&gt;\n &lt;a href=&quot;\nhttp://denis.stalker.h3q.com:6969/announce&quot; rel=&quot;nofollow&quot; target=&quot;_NEW&quot;&gt;\nhttp://denis.stalker.h3q.com:6969/announce&lt;/a&gt;\n\nudp://denis.stalker.h3q.com:6969/announce\n &lt;a href=&quot;\nhttp://www.sumotracker.com/announce&quot; rel=&quot;nofollow&quot; target=&quot;_NEW&quot;&gt;\nhttp://www.sumotracker.com/announce&lt;/a&gt;\n\n &lt;a href=&quot;\nhttp://bt1.the9.com:6969/announce&quot; rel=&quot;nofollow&quot; target=&quot;_NEW&quot;&gt;\nhttp://bt1.the9.com:6969/announce&lt;/a&gt;\n &lt;a href=&quot;\nhttp://exodus.desync.com:6969/announce&quot; rel=&quot;nofollow&quot; target=&quot;_NEW&quot;&gt;\nhttp://exodus.desync.com:6969/announce&lt;/a&gt;\n &lt;a href=&quot;\nhttp://genesis.1337x.org:1337/announce&quot; rel=&quot;nofollow&quot; target=&quot;_NEW&quot;&gt;\nhttp://genesis.1337x.org:1337/announce&lt;/a&gt;\n &lt;a href=&quot;\nhttp://nemesis.1337x.org:80/announce&quot; rel=&quot;nofollow&quot; target=&quot;_NEW&quot;&gt;\nhttp://nemesis.1337x.org:80/announce&lt;/a&gt;\n\nWe Are Looking For Early Access To Anything You Can Provide CAMS, TS, DVD Screeners, VHS Screeners, DVDRips, Direct Audio, Early Music Releases - Contact Us @ &lt;a class=&quot;__cf_email__&quot; href=&quot;/cdn-cgi/l/email-protection&quot; data-cfemail=&quot;1c6f73696e7f796f5c7775727b78737131776a7f7832727968&quot;&gt;[email&amp;#160;protected]&lt;/a&gt;&lt;script cf-hash='f9e31' type=&quot;text/javascript&quot;&gt;\n/* &lt;![CDATA[ */!function(){try{var t=&quot;currentScript&quot;in document?document.currentScript:function(){for(var t=document.getElementsByTagName(&quot;script&quot;),e=t.length;e--;)if(t[e].getAttribute(&quot;cf-hash&quot;))return t[e]}();if(t&amp;&amp;t.previousSibling){var e,r,n,i,c=t.previousSibling,a=c.getAttribute(&quot;data-cfemail&quot;);if(a){for(e=&quot;&quot;,r=parseInt(a.substr(0,2),16),n=2;a.length-n;n+=2)i=parseInt(a.substr(n,2),16)^r,e+=String.fromCharCode(i);e=document.createTextNode(e),c.parentNode.replaceChild(e,c)}}}catch(u){}}();/* ]]&gt; */&lt;/script&gt;\n\nGreets: KingBen, BLaZE, KK, Paulx1, DiNGiE, MaZZa, Richie, - All Of Kingdom, UKB &amp; Release-Lounge, Stuffies, IMAGiNE, ELEKTRI4KA, The GRiM, Ho's, CHD, IPT, EPIDEMZ, RELIZLAB, ExtraTorrent,FLAWL3SS, Framestor, 1337x, BSBT, And Many More. ;)\n\nNote: A video sample is included in the folder for those who want to check quality and compatibility before downloading the whole movie. And don't fall for fakes, grab our encodes from the source @ kingdom-kvcd.net or from our trusted accounts elsewhere.","torrent":{"xt":"urn:btih:f226c37330420451e6e18aef3414e3e77881a3bd","amp;dn":"The+Dark+Knight+2008+BRRip+720p+x264+Illidan91+%28Kingdom-Release%29","amp;tr":["udp%3A%2F%2Ftracker.openbittorrent.com%3A80","udp%3A%2F%2Fopen.demonii.com%3A1337","udp%3A%2F%2Ftracker.coppersurfer.tk%3A6969","udp%3A%2F%2Fexodus.desync.com%3A6969"],"infoHash":"f226c37330420451e6e18aef3414e3e77881a3bd","infoHashBuffer":{"type":"Buffer","data":[242,38,195,115,48,66,4,81,230,225,138,239,52,20,227,231,120,129,163,189]},"announce":[],"urlList":[]}}