{"title":"MonstersOfCock - Bella Reese (Girl Deepthroats a Monster Cock)","uid":7030458,"size":389305616,"categoryP":"porn","categoryS":"movies","magnet":"?xt=urn:btih:f41fa32fe7dd565c60364244aad3d966341aa8ed&amp;dn=MonstersOfCock+-+Bella+Reese+%28Girl+Deepthroats+a+Monster+Cock%29&amp;tr=udp%3A%2F%2Ftracker.openbittorrent.com%3A80&amp;tr=udp%3A%2F%2Fopen.demonii.com%3A1337&amp;tr=udp%3A%2F%2Ftracker.coppersurfer.tk%3A6969&amp;tr=udp%3A%2F%2Fexodus.desync.com%3A6969","seeders":1,"leechers":0,"uploader":"kelvin09","files":1,"time":1329204175,"description":"MonstersOfCock - Bella Reese (Girl Deepthroats a Monster Cock)\n\n &lt;a href=&quot;\nhttp://www.seedimage.com/IMG/viewer.php?file=71507311152254267959.jpg&quot; rel=&quot;nofollow&quot; target=&quot;_NEW&quot;&gt;\nhttp://www.seedimage.com/IMG/viewer.php?file=71507311152254267959.jpg&lt;/a&gt;\n &lt;a href=&quot;\nhttp://www.seedimage.com/IMG/viewer.php?file=47169861988395331843.jpg&quot; rel=&quot;nofollow&quot; target=&quot;_NEW&quot;&gt;\nhttp://www.seedimage.com/IMG/viewer.php?file=47169861988395331843.jpg&lt;/a&gt;\n\n\nThis week we have the beautiful Bella Reese taking on the monstrous Sean Michaels in what has to be one of our best monsters of cocks. Bella is one smoking hott Italian with an ass and a set of tits to wow anyone. she takes pride in her dick sucking skills but shes never had a a monster cock. so naturally she wanted to see how deep she could go with this beast of a cock in her mouth. and surprisingly she managed to deep through Sean with no problem. were talking balls deep here Ladies and Gentlemen!","torrent":{"xt":"urn:btih:f41fa32fe7dd565c60364244aad3d966341aa8ed","amp;dn":"MonstersOfCock+-+Bella+Reese+%28Girl+Deepthroats+a+Monster+Cock%29","amp;tr":["udp%3A%2F%2Ftracker.openbittorrent.com%3A80","udp%3A%2F%2Fopen.demonii.com%3A1337","udp%3A%2F%2Ftracker.coppersurfer.tk%3A6969","udp%3A%2F%2Fexodus.desync.com%3A6969"],"infoHash":"f41fa32fe7dd565c60364244aad3d966341aa8ed","infoHashBuffer":{"type":"Buffer","data":[244,31,163,47,231,221,86,92,96,54,66,68,170,211,217,102,52,26,168,237]},"announce":[],"urlList":[]}}