{"title":"UK Subs - A.W.O.L","uid":4576440,"size":372884256,"categoryP":"audio","categoryS":"music","magnet":"?xt=urn:btih:f55e80f148c296c515e6f14c7c6d52a533dab388&amp;dn=UK+Subs+-+A.W.O.L&amp;tr=udp%3A%2F%2Ftracker.openbittorrent.com%3A80&amp;tr=udp%3A%2F%2Fopen.demonii.com%3A1337&amp;tr=udp%3A%2F%2Ftracker.coppersurfer.tk%3A6969&amp;tr=udp%3A%2F%2Fexodus.desync.com%3A6969","seeders":1,"leechers":0,"uploader":"TosoZg","files":12,"time":1229253165,"description":"UK Subs - A.W.O.L, wave format ripped by EAC from original CD, enjoy and seed","torrent":{"xt":"urn:btih:f55e80f148c296c515e6f14c7c6d52a533dab388","amp;dn":"UK+Subs+-+A.W.O.L","amp;tr":["udp%3A%2F%2Ftracker.openbittorrent.com%3A80","udp%3A%2F%2Fopen.demonii.com%3A1337","udp%3A%2F%2Ftracker.coppersurfer.tk%3A6969","udp%3A%2F%2Fexodus.desync.com%3A6969"],"infoHash":"f55e80f148c296c515e6f14c7c6d52a533dab388","infoHashBuffer":{"type":"Buffer","data":[245,94,128,241,72,194,150,197,21,230,241,76,124,109,82,165,51,218,179,136]},"announce":[],"urlList":[]}}