{"title":"Madness -The Liberty of Norton Folgate (2009)","uid":4755128,"size":49953826,"categoryP":"audio","categoryS":"music","magnet":"?xt=urn:btih:f9745675e8ab93998027de08f27b6758102010c0&amp;dn=Madness+-The+Liberty+of+Norton+Folgate+%282009%29&amp;tr=udp%3A%2F%2Ftracker.openbittorrent.com%3A80&amp;tr=udp%3A%2F%2Fopen.demonii.com%3A1337&amp;tr=udp%3A%2F%2Ftracker.coppersurfer.tk%3A6969&amp;tr=udp%3A%2F%2Fexodus.desync.com%3A6969","seeders":1,"leechers":0,"uploader":"el_abuelo","files":13,"time":1236416527,"description":"01 We Are London\n02 Forever Young\n03 Dust Devil\n04 The Liberty Of Norton Folgate\n05 Sugar And Spice\n06 Clerkenwell Polka\n07 Bingo\n08 Rainbows\n09 That Close\n10 MkII\n11 Idiot Child\n12 On The Town","torrent":{"xt":"urn:btih:f9745675e8ab93998027de08f27b6758102010c0","amp;dn":"Madness+-The+Liberty+of+Norton+Folgate+%282009%29","amp;tr":["udp%3A%2F%2Ftracker.openbittorrent.com%3A80","udp%3A%2F%2Fopen.demonii.com%3A1337","udp%3A%2F%2Ftracker.coppersurfer.tk%3A6969","udp%3A%2F%2Fexodus.desync.com%3A6969"],"infoHash":"f9745675e8ab93998027de08f27b6758102010c0","infoHashBuffer":{"type":"Buffer","data":[249,116,86,117,232,171,147,153,128,39,222,8,242,123,103,88,16,32,16,192]},"announce":[],"urlList":[]}}