{"title":"Weather Report - Live and Unreleased (2002) [2CD] [EAC-FLAC]","uid":9193909,"size":979036219,"categoryP":"audio","categoryS":"flac","magnet":"?xt=urn:btih:fab42e985504dd0233f17076be7067bfa75f5384&amp;dn=Weather+Report+-+Live+and+Unreleased+%282002%29+%5B2CD%5D+%5BEAC-FLAC%5D&amp;tr=udp%3A%2F%2Ftracker.openbittorrent.com%3A80&amp;tr=udp%3A%2F%2Fopen.demonii.com%3A1337&amp;tr=udp%3A%2F%2Ftracker.coppersurfer.tk%3A6969&amp;tr=udp%3A%2F%2Fexodus.desync.com%3A6969","seeders":1,"leechers":0,"uploader":"qculfj","files":34,"time":1384445431,"description":"CD1:\n\n01. Freezing Fire - 8:14\n02. Plaza Real - 7:04\n03. Fast City - 6:49\n04. Portrait Of Tracy - 5:57\n05. Elegant People - 4:28\n06. Cucumber Slumber - 11:39\n07. Teen Town - 6:30\n08. Man In The Green Shirt - 10:31\n\nCD2:\n\n01. Black Market - 9:26\n02. Where The Moon Goes - 12:05\n03. River People - 6:57\n04. Two Lines - 8:15\n05. Cigano - 3:59\n06. In A Silent Way/Waterfall - 5:46\n07. Night Passage - 5:53\n08. Port Of Entry - 8:08\n09. Rumba Mama - 1:15\n10. Directions/Dr. Honoris Causa - 8:38","torrent":{"xt":"urn:btih:fab42e985504dd0233f17076be7067bfa75f5384","amp;dn":"Weather+Report+-+Live+and+Unreleased+%282002%29+%5B2CD%5D+%5BEAC-FLAC%5D","amp;tr":["udp%3A%2F%2Ftracker.openbittorrent.com%3A80","udp%3A%2F%2Fopen.demonii.com%3A1337","udp%3A%2F%2Ftracker.coppersurfer.tk%3A6969","udp%3A%2F%2Fexodus.desync.com%3A6969"],"infoHash":"fab42e985504dd0233f17076be7067bfa75f5384","infoHashBuffer":{"type":"Buffer","data":[250,180,46,152,85,4,221,2,51,241,112,118,190,112,103,191,167,95,83,132]},"announce":[],"urlList":[]}}