{"title":"Japan AV -Hitomi Hayasaka Bank Bukkake--8m10s.avi","uid":9535669,"size":33322914,"categoryP":"porn","categoryS":"movie_clips","magnet":"?xt=urn:btih:fabc136b233f1efd819a0137cdbd8e5e23ff00ea&amp;dn=Japan+AV+-Hitomi+Hayasaka+Bank+Bukkake--8m10s.avi&amp;tr=udp%3A%2F%2Ftracker.openbittorrent.com%3A80&amp;tr=udp%3A%2F%2Fopen.demonii.com%3A1337&amp;tr=udp%3A%2F%2Ftracker.coppersurfer.tk%3A6969&amp;tr=udp%3A%2F%2Fexodus.desync.com%3A6969","seeders":1,"leechers":1,"uploader":"sunny1969","files":-1,"time":1390926324,"description":"Hitomi Hayasaka bank bukkake.\n &lt;a href=&quot;\nhttp://bayimg.com/GAhKeAafp&quot; rel=&quot;nofollow&quot; target=&quot;_NEW&quot;&gt;\nhttp://bayimg.com/GAhKeAafp&lt;/a&gt;","torrent":{"xt":"urn:btih:fabc136b233f1efd819a0137cdbd8e5e23ff00ea","amp;dn":"Japan+AV+-Hitomi+Hayasaka+Bank+Bukkake--8m10s.avi","amp;tr":["udp%3A%2F%2Ftracker.openbittorrent.com%3A80","udp%3A%2F%2Fopen.demonii.com%3A1337","udp%3A%2F%2Ftracker.coppersurfer.tk%3A6969","udp%3A%2F%2Fexodus.desync.com%3A6969"],"infoHash":"fabc136b233f1efd819a0137cdbd8e5e23ff00ea","infoHashBuffer":{"type":"Buffer","data":[250,188,19,107,35,63,30,253,129,154,1,55,205,189,142,94,35,255,0,234]},"announce":[],"urlList":[]}}